{"is_source_file": true, "format": "JavaScript/JSX", "description": "React component for displaying the details of a playlist, including its metadata and list of tracks, with functionality to load playlist data, handle loading/error states, and initiate playback.", "external_files": ["../hooks/useAuth", "../components/ui/Skeleton", "../components/ui/Button", "../components/TrackList", "../hooks/usePagination", "../state/playerStore"], "external_methods": ["useParams", "useAuth", "usePlayer", "usePagination", "useState", "useEffect", "useCallback"], "published": [], "classes": [], "methods": [{"name": "PlaylistDetail()", "description": "Main React component to display playlist details including cover, name, description, and tracks, with controls for playing tracks and loading more.", "scope": "", "scopeKind": ""}, {"name": "normalizeList(data)", "description": "Utility function to normalize playlist data into a consistent list format.", "scope": "PlaylistDetail", "scopeKind": "function"}, {"name": "mapTrack(t)", "description": "Utility function to map track object to include an 'audioUrl' property.", "scope": "PlaylistDetail", "scopeKind": "function"}, {"name": "load()", "scope": "PlaylistDetail", "scopeKind": "function", "description": "unavailable"}], "calls": ["api.get", "setMeta", "setErrorMeta", "setLoadingMeta", "playPlaylist", "playTrack", "tracks.loadMore"], "search-terms": ["PlaylistDetail.jsx", "React playlist page", "usePagination with playlist tracks", "load playlist info", "track list rendering", "play playlist button"], "state": 2, "file_id": 43, "knowledge_revision": 111, "git_revision": "72a9f4225de03e096ff7c60a73e7a67c860b263f", "revision_history": [{"94": ""}, {"111": "72a9f4225de03e096ff7c60a73e7a67c860b263f"}], "ctags": [{"_type": "tag", "name": "PlaylistDetail", "path": "/home/kavia/workspace/code-generation/music-streamer-199976-200027/frontend_react/src/pages/PlaylistDetail.jsx", "pattern": "/^export default function PlaylistDetail() {$/", "language": "JavaScript", "kind": "function", "signature": "()"}, {"_type": "tag", "name": "load", "path": "/home/kavia/workspace/code-generation/music-streamer-199976-200027/frontend_react/src/pages/PlaylistDetail.jsx", "pattern": "/^    async function load() {$/", "language": "JavaScript", "kind": "function", "signature": "()", "scope": "PlaylistDetail", "scopeKind": "function"}, {"_type": "tag", "name": "mapTrack", "path": "/home/kavia/workspace/code-generation/music-streamer-199976-200027/frontend_react/src/pages/PlaylistDetail.jsx", "pattern": "/^function mapTrack(t) {$/", "language": "JavaScript", "kind": "function", "signature": "(t)", "scope": "PlaylistDetail", "scopeKind": "function"}, {"_type": "tag", "name": "normalizeList", "path": "/home/kavia/workspace/code-generation/music-streamer-199976-200027/frontend_react/src/pages/PlaylistDetail.jsx", "pattern": "/^function normalizeList(data) {$/", "language": "JavaScript", "kind": "function", "signature": "(data)", "scope": "PlaylistDetail", "scopeKind": "function"}, {"_type": "tag", "name": "tracks", "path": "/home/kavia/workspace/code-generation/music-streamer-199976-200027/frontend_react/src/pages/PlaylistDetail.jsx", "pattern": "/^          loading={tracks.loading && tracks.items.length === 0}$/", "language": "JavaScript", "kind": "field", "scope": "PlaylistDetail.loading", "scopeKind": "class"}, {"_type": "tag", "name": "tracks", "path": "/home/kavia/workspace/code-generation/music-streamer-199976-200027/frontend_react/src/pages/PlaylistDetail.jsx", "pattern": "/^          tracks={tracks.items}$/", "language": "JavaScript", "kind": "field", "scope": "PlaylistDetail.tracks", "scopeKind": "class"}], "hash": "c1dabec9251e79ed8fe0fed1c6179268", "format-version": 4, "code-base-name": "frontend_react", "filename": "frontend_react/src/pages/PlaylistDetail.jsx", "fields": [{"name": "loading={tracks.loading && tracks.items.length === 0}", "scope": "PlaylistDetail.loading", "scopeKind": "class", "description": "unavailable"}, {"name": "tracks={tracks.items}", "scope": "PlaylistDetail.tracks", "scopeKind": "class", "description": "unavailable"}]}