{"is_source_file": false, "format": "", "description": "", "external_files": [], "external_methods": [], "published": [], "classes": [], "methods": [], "calls": [], "search-terms": [], "state": 2, "file_id": 4, "knowledge_revision": 40, "git_revision": "6f0df3f745b085de12cd51139810215763c9b249", "hash": "1a3449c66fc67ac86fa4785e4439536b", "format-version": 4, "code-base-name": "frontend_react", "filename": "frontend_react/src/index.css", "revision_history": [{"40": "6f0df3f745b085de12cd51139810215763c9b249"}]}